mathwork/__init__.py
mathwork/mathwork.py
mathwork/Lab Manuals/CV Lab 01.pdf
mathwork/Lab Manuals/CV Lab-01.pdf
mathwork/Lab Manuals/CV Lab-02.pdf
mathwork/Lab Manuals/CV Lab-03.pdf
mathwork/Lab Manuals/CV Lab-04.pdf
mathwork/Lab Manuals/CV Lab-05.pdf
mathwork/Lab Manuals/CV Lab-06-CNN.pdf
mathwork/Lab Manuals/CV Lab-06.pdf
mathwork/Lab Manuals/CV Lab-08.pdf
mathwork/Lab Manuals/CV Lab-11.pdf
mathwork/Lab Manuals/CV Lab-12.pdf
mathwork/Lab Tasks/1 4703.ipynb
mathwork/Lab Tasks/1 isloo.JPG
mathwork/Lab Tasks/2 4703.ipynb
mathwork/Lab Tasks/2 isloo.JPG
mathwork/Lab Tasks/3 4703.ipynb
mathwork/Lab Tasks/3 isloo.JPG
mathwork/Lab Tasks/4 4703.ipynb
"mathwork/Lab Tasks/5,6 4703.ipynb"
mathwork/Lab Tasks/8 4703 yolo.ipynb
mathwork/Lab Tasks/ALEXNET.ipynb
mathwork/Lab Tasks/AlexNet 4703.ipynb
mathwork/Lab Tasks/Autoencoders.ipynb
mathwork/Lab Tasks/CNN and LSTM.ipynb
mathwork/Lab Tasks/CV Lab 1.ipynb
mathwork/Lab Tasks/CV Labs 2.ipynb
mathwork/Lab Tasks/CV lab -2.ipynb
mathwork/Lab Tasks/CV_Lab_04.ipynb
mathwork/Lab Tasks/CV_Lab_06.ipynb
mathwork/Lab Tasks/Chest_xray.jpeg
mathwork/Lab Tasks/DCGAN_Lab_09.ipynb
mathwork/Lab Tasks/Ethernet-H264 75.mp4
mathwork/Lab Tasks/Foot_mri.jpeg
mathwork/Lab Tasks/Foot_xrays.jpeg
"mathwork/Lab Tasks/Lab 10 1,2,3,5.ipynb"
mathwork/Lab Tasks/Lab 6 t1.zip
mathwork/Lab Tasks/Lab 6 t2.ipynb
mathwork/Lab Tasks/Lab 6 t3.ipynb
mathwork/Lab Tasks/Lab 6 t4.ipynb
mathwork/Lab Tasks/Lab 6 t5.ipynb
mathwork/Lab Tasks/Lab 9 B.ipynb
mathwork/Lab Tasks/Lab 9 t1.ipynb
mathwork/Lab Tasks/Lab 9 t2.ipynb
mathwork/Lab Tasks/Lab 9 t3.ipynb
mathwork/Lab Tasks/RCNN.ipynb
mathwork/Lab Tasks/VGG16_Transfer_Learning_.ipynb
mathwork/Lab Tasks/Variational_Autoencoders.ipynb
mathwork/Lab Tasks/ViT FashionMnist .ipynb
mathwork/Lab Tasks/ViT MNIST.ipynb
mathwork/Lab Tasks/ViT_Image_Classificatoin.ipynb
mathwork/Lab Tasks/Yolov8.ipynb
mathwork/Lab Tasks/anomaly_detection_autoencoders.ipynb
mathwork/Lab Tasks/asim.jpeg
mathwork/Lab Tasks/car.JPG
mathwork-1.8.dist-info/METADATA
mathwork-1.8.dist-info/WHEEL
mathwork-1.8.dist-info/dependency_links.txt
mathwork-1.8.dist-info/top_level.txt
mathwork-1.8.dist-info/RECORD
