Metadata-Version: 2.1
Name: mathwork
Version: 1.8
Summary: The great package.
Author: unknown
Requires-Dist: tensorflow
Requires-Dist: pandas
Requires-Dist: scikit-learn
Requires-Dist: torch
Requires-Dist: opencv-python
Requires-Dist: pillow
Requires-Dist: scikit-image
Requires-Dist: numpy
Requires-Dist: scipy
Requires-Dist: matplotlib
Requires-Dist: pywavelets
Requires-Dist: seaborn
Requires-Dist: torchvision
Requires-Dist: torchaudio
Requires-Dist: keras
Requires-Dist: transformers
Requires-Dist: tqdm
Requires-Dist: ultralytics
